{
  "action_queues": {
    "install": [
      {
        "install_folder": "storage",
        "name": "minio-s3"
      },
      {
        "install_folder": "cicd",
        "name": "argocd"
      },
      {
        "install_folder": "monitoring",
        "name": "grafana"
      },
      {
        "install_folder": "cicd",
        "name": "harbor"
      },
      {
        "install_folder": "cicd",
        "name": "gitlab-ce"
      },
      {
        "install_folder": "quality_assurance",
        "name": "sonarqube"
      }
    ]
  }
}
