{
    "name": "influxdb2",
    "namespace": "influxdata",
    "installation_type": "helm",
    "installation_group_folder": "monitoring",
    "environment_variables": {
        "imageTag": "2.1.1-alpine"
    },
    "helm_params": {
        "repository_url": "https://helm.influxdata.com/",
        "repository_name": "influxdata/influxdb2",
        "helm_version": "2.0.11",
        "set_key_values": []
    },
    "categories": [
        "time-series",
        "database"
    ],
    "urls": [
        {
            "url": "https://{{componentName}}.{{baseDomain}}",
            "healthchecks": {
                "liveliness": {
                    "http_path": "/",
                    "http_auth_required": false,
                    "expected_http_response_code": "200",
                    "expected_http_response_string": "",
                    "expected_json_response": {
                        "json_path": "",
                        "json_value": ""
                    },
                    "health_shell_check_command": "",
                    "expected_shell_check_command_response": ""
                },
                "readiness": {
                    "http_path": "/",
                    "http_auth_required": false,
                    "expected_http_response_code": "200",
                    "expected_http_response_string": "",
                    "expected_json_response": {
                        "json_path": "",
                        "json_value": ""
                    },
                    "health_shell_check_command": "",
                    "expected_shell_check_command_response": ""
                }
            }
        }
    ],
    "Description": "InfluxDB2 Description",
    "shortcut_text": "InfluxDB2",
    "shortcut_icon": "influxdb2.png",
    "pre_install_scripts": [
        "createAuthSecret.sh"
    ],
    "post_install_scripts": []
}
