{
  "sharedKxHome": "/usr/share/kx.as.code",
  "installationWorkspace": "${sharedKxHome}/workspace",
  "profileConfigJsonPath": "${installationWorkspace}/profile-config.json",
  "certificatesWorkspace": "${installationWorkspace}/certificates",
  "actionWorkflows": "pending wip completed failed retry notification skipped",
  "coreGopassGroups": "remote-desktop openldap keycloak docker-registry",
  "defaultDockerHubSecret": "default/regcred",
  "sharedGitHome": "${sharedKxHome}/git",
  "autoSetupHome": "${sharedGitHome}/kx.as.code/auto-setup",
  "skelDirectory": "${sharedKxHome}/skel",
  "vendorDocsDirectory": "${sharedKxHome}/Vendor Docs",
  "apiDocsDirectory": "${sharedKxHome}/API Docs",
  "shortcutsDirectory": "${sharedKxHome}/Applications",
  "applicationShortcutsDirectory": "${sharedKxHome}/Applications",
  "taskShortcutsDirectory": "${sharedKxHome}/Tasks",
  "logsDirectory": "${sharedKxHome}/Logs",
  "adminShortcutsDirectory": "${sharedKxHome}/Admin Tools",
  "vmUser": "kx.hero",
  "vmUserId": "$(id -u ${vmUser})",
  "vmPassword": "$(cat ${sharedKxHome}/.config/.user.cred)",
  "kanikoVersion": "v1.9.0",
  "colourGreen": "33FFAC",
  "colourBlue": "33A2FF",
  "colourRed": "FA1806",
  "colourAmber": "FF7401",
  "colourGrey": "A29E97",
  "ansiRed": "\\\u001b[31m",
  "ansiGreen": "\\\u001b[32m",
  "ansiOrange": "\\\u001b[33m",
  "ansiBlue": "\\\u001b[36m",
  "ansiReset": "\\\u001b[0m"
}
